jupyterlab_bpmn/__init__.py
jupyterlab_bpmn/_version.py
jupyterlab_bpmn-0.5.6.data/data/share/jupyter/labextensions/jupyterlab-bpmn/package.json
jupyterlab_bpmn-0.5.6.data/data/share/jupyter/labextensions/jupyterlab-bpmn/static/124.18854ff03f8b9581c6e6.js
jupyterlab_bpmn-0.5.6.data/data/share/jupyter/labextensions/jupyterlab-bpmn/static/237.08b1b1b697a0470ac7ea.js
jupyterlab_bpmn-0.5.6.data/data/share/jupyter/labextensions/jupyterlab-bpmn/static/298.2ecaa790fdc9b82d5a0e.js
jupyterlab_bpmn-0.5.6.data/data/share/jupyter/labextensions/jupyterlab-bpmn/static/534.21d75e468256b183e87f.js
jupyterlab_bpmn-0.5.6.data/data/share/jupyter/labextensions/jupyterlab-bpmn/static/554.2df06ff9ee8468945e9a.js
jupyterlab_bpmn-0.5.6.data/data/share/jupyter/labextensions/jupyterlab-bpmn/static/670.f5812967c49554f2b09c.js
jupyterlab_bpmn-0.5.6.data/data/share/jupyter/labextensions/jupyterlab-bpmn/static/698.053bb4a7a56617826283.js
jupyterlab_bpmn-0.5.6.data/data/share/jupyter/labextensions/jupyterlab-bpmn/static/747.8722af89e64fd2a602a2.js
jupyterlab_bpmn-0.5.6.data/data/share/jupyter/labextensions/jupyterlab-bpmn/static/948.bd82d20c94e964ef570b.js
jupyterlab_bpmn-0.5.6.data/data/share/jupyter/labextensions/jupyterlab-bpmn/static/remoteEntry.eab2517eeab9baf74621.js
jupyterlab_bpmn-0.5.6.data/data/share/jupyter/labextensions/jupyterlab-bpmn/static/style.js
jupyterlab_bpmn-0.5.6.data/data/share/jupyter/labextensions/jupyterlab-bpmn/static/third-party-licenses.json
jupyterlab_bpmn-0.5.6.data/data/share/jupyter/labextensions/jupyterlab-bpmn/install.json
jupyterlab_bpmn-0.5.6.dist-info/METADATA
jupyterlab_bpmn-0.5.6.dist-info/WHEEL
jupyterlab_bpmn-0.5.6.dist-info/licenses/LICENSE
jupyterlab_bpmn-0.5.6.dist-info/RECORD
